{
  "CTk": {
      "fg_color": ["#F5F5DC", "#F5F5DC"]
  },
  "CTkToplevel": {
      "fg_color": ["#F5F5DC", "#F5F5DC"]
  },
  "CTkFrame": {
      "corner_radius": 6,
      "border_width": 0,
      "fg_color": ["#E0E0C0", "#E0E0C0"],
      "top_fg_color": ["#D0D0B0", "#D0D0B0"],
      "border_color": ["#A0A090", "#A0A090"]
  },
  "CTkButton": {
      "corner_radius": 6,
      "border_width": 0,
      "fg_color": ["#B49D80", "#B49D80"],
      "hover_color": ["#A08B70", "#A08B70"],
      "border_color": ["#5A4E44", "#5A4E44"],
      "text_color": ["#111111", "#111111"],
      "text_color_disabled": ["#808080", "#808080"]
  },
  "CTkLabel": {
      "corner_radius": 0,
      "fg_color": "transparent",
      "text_color": ["#111111", "#111111"]
  },
  "CTkEntry": {
      "corner_radius": 6,
      "border_width": 2,
      "fg_color": ["#F9F7E0", "#F9F7E0"],
      "border_color": ["#B49D80", "#B49D80"],
      "text_color": ["#111111", "#111111"],
      "placeholder_text_color": ["#878787", "#878787"]
  },
  "CTkCheckBox": {
      "corner_radius": 6,
      "border_width": 3,
      "fg_color": ["#C7C7A7", "#C7C7A7"],
      "border_color": ["#B49D80", "#B49D80"],
      "hover_color": ["#B7B797", "#B7B797"],
      "checkmark_color": ["#111111", "#111111"],
      "text_color": ["#111111", "#111111"],
      "text_color_disabled": ["#808080", "#808080"]
  },
  "CTkSwitch": {
      "corner_radius": 1000,
      "border_width": 3,
      "button_length": 0,
      "fg_color": ["#E0E0C0", "#E0E0C0"],
      "progress_color": ["#B49D80", "#B49D80"],
      "button_color": ["#8B7A66", "#8B7A66"],
      "button_hover_color": ["#7B6A56", "#7B6A56"],
      "text_color": ["#111111", "#111111"],
      "text_color_disabled": ["#808080", "#808080"]
  },
  "CTkRadioButton": {
      "corner_radius": 1000,
      "border_width_checked": 6,
      "border_width_unchecked": 3,
      "fg_color": ["#C7C7A7", "#C7C7A7"],
      "border_color": ["#B49D80", "#B49D80"],
      "hover_color": ["#B7B797", "#B7B797"],
      "text_color": ["#111111", "#111111"],
      "text_color_disabled": ["#808080", "#808080"]
  },
  "CTkProgressBar": {
      "corner_radius": 1000,
      "border_width": 0,
      "fg_color": ["#E0E0C0", "#E0E0C0"],
      "progress_color": ["#B49D80", "#B49D80"],
      "border_color": ["#A0A090", "#A0A090"]
  },
  "CTkSlider": {
      "corner_radius": 1000,
      "button_corner_radius": 1000,
      "border_width": 6,
      "button_length": 0,
      "fg_color": ["#E0E0C0", "#E0E0C0"],
      "progress_color": ["#A0A090", "#A0A090"],
      "button_color": ["#B49D80", "#B49D80"],
      "button_hover_color": ["#A08B70", "#A08B70"]
  },
  "CTkOptionMenu": {
      "corner_radius": 6,
      "fg_color": ["#B49D80", "#B49D80"],
      "button_color": ["#A08B70", "#A08B70"],
      "button_hover_color": ["#8B7A66", "#8B7A66"],
      "text_color": ["#111111", "#111111"],
      "text_color_disabled": ["#808080", "#808080"]
  },
  "CTkComboBox": {
      "corner_radius": 6,
      "border_width": 2,
      "fg_color": ["#F9F7E0", "#F9F7E0"],
      "border_color": ["#B49D80", "#B49D80"],
      "button_color": ["#B49D80", "#B49D80"],
      "button_hover_color": ["#A08B70", "#A08B70"],
      "text_color": ["#111111", "#111111"],
      "text_color_disabled": ["#808080", "#808080"]
  },
  "CTkScrollbar": {
      "corner_radius": 1000,
      "border_spacing": 4,
      "fg_color": "transparent",
      "button_color": ["#B49D80", "#B49D80"],
      "button_hover_color": ["#A08B70", "#A08B70"]
  },
  "CTkSegmentedButton": {
      "corner_radius": 6,
      "border_width": 2,
      "fg_color": ["#E0E0C0", "#E0E0C0"],
      "selected_color": ["#B49D80", "#B49D80"],
      "selected_hover_color": ["#A08B70", "#A08B70"],
      "unselected_color": ["#E0E0C0", "#E0E0C0"],
      "unselected_hover_color": ["#D0D0B0", "#D0D0B0"],
      "text_color": ["#111111", "#111111"],
      "text_color_disabled": ["#808080", "#808080"]
  },
  "CTkTextbox": {
      "corner_radius": 6,
      "border_width": 0,
      "fg_color": ["#F9F7E0", "#F9F7E0"],
      "border_color": ["#B49D80", "#B49D80"],
      "text_color": ["#111111", "#111111"],
      "scrollbar_button_color": ["#B49D80", "#B49D80"],
      "scrollbar_button_hover_color": ["#A08B70", "#A08B70"]
  },
  "CTkScrollableFrame": {
      "label_fg_color": ["#D0D0B0", "#D0D0B0"]
  },
  "DropdownMenu": {
      "fg_color": ["#E0E0C0", "#E0E0C0"],
      "hover_color": ["#D0D0B0", "#D0D0B0"],
      "text_color": ["#111111", "#111111"]
  },
  "CTkFont": {
      "macOS": {
          "family": "SF Display",
          "size": 13,
          "weight": "normal"
      },
      "Windows": {
          "family": "Roboto",
          "size": 13,
          "weight": "normal"
      },
      "Linux": {
          "family": "Roboto",
          "size": 13,
          "weight": "normal"
      }
  }
}